LICENSE
MANIFEST.in
README.md
README.rst
setup.py
pyProCT_GUI.egg-info/PKG-INFO
pyProCT_GUI.egg-info/SOURCES.txt
pyProCT_GUI.egg-info/dependency_links.txt
pyProCT_GUI.egg-info/requires.txt
pyProCT_GUI.egg-info/top_level.txt
pyproctgui/__init__.py
pyproctgui/gui/__init__.py
pyproctgui/gui/browsing.py
pyproctgui/gui/exceptionThread.py
pyproctgui/gui/execution.py
pyproctgui/gui/main.py
pyproctgui/gui/pdbSelection.py
pyproctgui/gui/serverHandler.py
pyproctgui/gui/static/index.html
pyproctgui/gui/static/results.html
pyproctgui/gui/static/results/css/cluster_widget.css
pyproctgui/gui/static/results/css/style.css
pyproctgui/gui/static/results/css/jquery/jqplot/jquery.jqplot.min.css
pyproctgui/gui/static/results/img/collapsed.png
pyproctgui/gui/static/results/img/compressed_pdb.png
pyproctgui/gui/static/results/img/expanded.png
pyproctgui/gui/static/results/img/image.png
pyproctgui/gui/static/results/img/pdb.png
pyproctgui/gui/static/results/img/text.png
pyproctgui/gui/static/results/img/triangles_big.png
pyproctgui/gui/static/results/js/clusters.js
pyproctgui/gui/static/results/js/dialogs.js
pyproctgui/gui/static/results/js/displacements.js
pyproctgui/gui/static/results/js/distances.js
pyproctgui/gui/static/results/js/evaluation.js
pyproctgui/gui/static/results/js/expand_list.js
pyproctgui/gui/static/results/js/main.js
pyproctgui/gui/static/results/js/jquery/jquery.tablesorter.min.js
pyproctgui/gui/static/results/js/jquery/jqplot/excanvas.js
pyproctgui/gui/static/results/js/jquery/jqplot/jquery.jqplot.min.css
pyproctgui/gui/static/results/js/jquery/jqplot/jquery.jqplot.min.js
pyproctgui/gui/static/results/js/jquery/jqplot/plugins/jqplot.BezierCurveRenderer.js
pyproctgui/gui/static/results/js/jquery/jqplot/plugins/jqplot.BezierCurveRenderer.min.js
pyproctgui/gui/static/results/js/jquery/jqplot/plugins/jqplot.barRenderer.js
pyproctgui/gui/static/results/js/jquery/jqplot/plugins/jqplot.barRenderer.min.js
pyproctgui/gui/static/results/js/jquery/jqplot/plugins/jqplot.blockRenderer.js
pyproctgui/gui/static/results/js/jquery/jqplot/plugins/jqplot.blockRenderer.min.js
pyproctgui/gui/static/results/js/jquery/jqplot/plugins/jqplot.bubbleRenderer.js
