Metadata-Version: 1.0
Name: pyProCT-GUI
Version: 0.4.1
Summary: A Graphical User Interface for pyProCT clustering toolkit.
Home-page: https://github.com/victor-gil-sepulveda/pyProCT-GUI.git
Author: Victor Alejandro Gil Sepulveda
Author-email: victor.gil.sepulveda@gmail.com
License: LICENSE.txt
Platform: UNKNOWN
